Metadata-Version: 1.1
Name: webbridge
Version: 0.1
Summary: A bridge between pywebview and your web application.
Home-page: https://github.com/KinmanCovey/webbridge
Author: Kinman Covey
Author-email: kinmancovey@yahoo.com
License: UNKNOWN
Download-URL: https://github.com/KinmanCovey/webbridge/archive/master.zip
Keywords: bridge,html,gui,web,app
Platform: UNKNOWN
